acvr/__init__.py
acvr/_pyav_backend.py
acvr/reader.py
acvr-0.1.0.dist-info/licenses/LICENSE
acvr-0.1.0.dist-info/WHEEL
acvr-0.1.0.dist-info/METADATA
acvr-0.1.0.dist-info/RECORD
