Metadata-Version: 2.4
Name: acvr
Version: 0.1.0
Summary: Accurate video reader for python.
Author-email: Jan Clemens <clemensjan@googlemail.com>
Requires-Python: >=3.9
Classifier: License :: OSI Approved :: MIT License
License-File: LICENSE
Requires-Dist: av
Requires-Dist: numpy
Requires-Dist: opencv-python-headless ; extra == "dev"
Requires-Dist: pytest ; extra == "dev"
Requires-Dist: mkdocs ; extra == "docs"
Requires-Dist: mkdocs-shadcn ; extra == "docs"
Requires-Dist: mkdocstrings[python] ; extra == "docs"
Project-URL: Documentation, https://janclemenslab.org/acvr
Project-URL: Source, https://github.com/janclemenslab/acvr
Provides-Extra: dev
Provides-Extra: docs
